pydantic_flask/__init__.py
pydantic_flask/core.py
pydantic_flask/pydantic.py
pydantic_flask/types.py
pydantic_flask-0.1.1.dist-info/METADATA
pydantic_flask-0.1.1.dist-info/WHEEL
pydantic_flask-0.1.1.dist-info/RECORD
