Metadata-Version: 2.1
Name: pydantic-flask
Version: 0.1.1
Summary: 
Author: Abyssknight
Author-email: 501835725@qq.com
Requires-Python: >=3.9,<4.0
Classifier: Programming Language :: Python :: 3
Classifier: Programming Language :: Python :: 3.9
Classifier: Programming Language :: Python :: 3.10
Classifier: Programming Language :: Python :: 3.11
Requires-Dist: flask (>=2.0.0)
Requires-Dist: pydantic (>=2.0.0)
